{
  "title": "Global PALSAR-2/PALSAR Yearly Mosaic, version 1  |  Earth Engine Data Catalog  |  Google for Developers",
  "provider": "JAXA EORC",
  "tags": [
    "Gis Stack Exchange",
    "Medium",
    "Alos2",
    "Videos",
    "Palsar2",
    "Twitter",
    "Alos\nAlos2\nEroc\nJaxa\nPalsar\nPalsar2\nSar\nSatellite-Imagery",
    "Palsar",
    "Eroc",
    "Sar",
    "Satellite-Imagery",
    "Alos",
    "Jaxa",
    "Github"
  ],
  "date_range": "",
  "description": "...",
  "bands": [],
  "terms_of_use": "",
  "snippet": "",
  "spatial_coverage": "",
  "temporal_coverage": "",
  "citation": "",
  "type": "",
  "region": "",
  "source_url": "https://developers.google.com/earth-engine/datasets/catalog/JAXA_ALOS_PALSAR_YEARLY_SAR",
  "extraction_report": {},
  "confidence": {
    "title": 1.0,
    "description": 1.0,
    "tags": 0.9,
    "provider": 0.8
  },
  "ml_classification": {
    "spacy_entities": {
      "PERSON": [
        "Global PALSAR-2",
        "Yearly Mosaic",
        "Landsat\n   \n\n\n\n\n\n\n\n      MODIS"
      ],
      "CARDINAL": [
        "1"
      ],
      "ORG": [
        "Earth Engine Data Catalog",
        "Google for Developers\n\n\n\n\n\n\n\n\n\n\n\n\n\n\n\n\n\n\n      \n      Skip",
        "Deutsch\n\n\nEspañol\n\n\nEspañol – América Latina\n\n\nFrançais",
        "Italiano\n\n\nPolski\n\n\nPortuguês",
        "Türkçe"
      ],
      "NORP": [
        "English"
      ],
      "GPE": [
        "Indonesia",
        "বাংলা"
      ],
      "WORK_OF_ART": [
        "Home\n  \n    \n\n\n    Categories\n  \n    \n\n\n    All"
      ]
    },
    "title_entities": [
      [
        "Yearly Mosaic",
        "PERSON"
      ],
      [
        "1",
        "CARDINAL"
      ],
      [
        "Earth Engine Data Catalog",
        "ORG"
      ],
      [
        "Google for Developers",
        "ORG"
      ]
    ],
    "bert_classification": [
      {
        "label": "LABEL_1",
        "score": 0.5328359603881836
      }
    ]
  },
  "validation_results": {
    "spatial": {
      "valid": true,
      "errors": [],
      "enriched": {
        "spatial_scope": "global",
        "geocoded_location": {
          "name": "Global",
          "coordinates": [
            55.702215,
            12.5592485
          ]
        }
      }
    },
    "temporal": {
      "valid": false,
      "errors": [],
      "enriched": {}
    },
    "quality": {
      "valid": true,
      "score": 90,
      "errors": [],
      "enriched": {
        "quality_score": 90
      }
    }
  },
  "ensemble_features": {
    "tfidf_features": 11,
    "text_length": 103
  }
}